surfscraphb/__init__.py
surfscraphb/core.py
surfscraphb-0.0.1.dist-info/licenses/LICENSE
surfscraphb-0.0.1.dist-info/METADATA
surfscraphb-0.0.1.dist-info/WHEEL
surfscraphb-0.0.1.dist-info/top_level.txt
surfscraphb-0.0.1.dist-info/RECORD
