Metadata-Version: 2.4
Name: surfscraphb
Version: 0.0.1
Summary: Scrape surf  conditions from surf-report.com
Author: MISSONGO Aimé Blanchard, Hippolyte SODJINOU
License: MIT License
Project-URL: Homepage, https://github.com/Hippolyte90/surf-scrap-pack/tree/main/surf_project
Classifier: Development Status :: 3 - Alpha
Classifier: Programming Language :: Python :: 3
Classifier: License :: OSI Approved :: MIT License
Classifier: Operating System :: OS Independent
Requires-Python: >=3.12
License-File: LICENSE
Requires-Dist: requests
Requires-Dist: beautifulsoup4
Requires-Dist: lxml
Requires-Dist: pandas
Dynamic: license-file
